{"payload":{"statistics":{"performance_metrics":{"sMAPE":{"scope_1":0.061,"scope_2":0.057,"scope_3":0.067},"MAE":{"scope_1":452.705,"scope_2":738.754,"scope_3":2035.407}},"confidence_ratings":{"scope_1":{"<10.0%":88.157,"10-20%":5.653,"20-50%":3.614,"50-100%":0.823,"100-200%":0.394,">200.0%":1.36},"scope_2":{"<10.0%":89.41,"10-20%":5.367,"20-50%":2.934,"50-100%":0.823,"100-200%":0.322,">200.0%":1.145},"scope_3":{"<10.0%":84.83,"10-20%":6.905,"20-50%":5.152,"50-100%":1.395,"100-200%":0.644,">200.0%":1.073}},"meta":{"number_of_companies_in_the_test_set":8284,"number_of_data_points_in_the_test_set":13973}}},"metadata":{"message":"Success","status":200}}